botarena/__init__.py
botarena/cli.py
botarena/client.py
botarena/policy.py
botarena/runner.py
botarena/types.py
botarena_sdk-0.1.1.dist-info/METADATA
botarena_sdk-0.1.1.dist-info/WHEEL
botarena_sdk-0.1.1.dist-info/entry_points.txt
botarena_sdk-0.1.1.dist-info/top_level.txt
botarena_sdk-0.1.1.dist-info/RECORD
