Metadata-Version: 2.4
Name: botarena-sdk
Version: 0.1.1
Summary: Official Python SDK for Bot Arena - Robot Policy Competition Platform
Author-email: Bot Manifold <sdk@botmanifold.com>
License: MIT
Project-URL: Homepage, https://botmanifold.com
Project-URL: Documentation, https://docs.botmanifold.com
Project-URL: Repository, https://github.com/botmanifold/botarena
Project-URL: Issues, https://github.com/botmanifold/botarena/issues
Keywords: robotics,mujoco,simulation,competition,reinforcement-learning
Classifier: Development Status :: 3 - Alpha
Classifier: Intended Audience :: Developers
Classifier: Intended Audience :: Science/Research
Classifier: License :: OSI Approved :: MIT License
Classifier: Programming Language :: Python :: 3
Classifier: Programming Language :: Python :: 3.9
Classifier: Programming Language :: Python :: 3.10
Classifier: Programming Language :: Python :: 3.11
Classifier: Programming Language :: Python :: 3.12
Classifier: Topic :: Scientific/Engineering :: Artificial Intelligence
Classifier: Topic :: Scientific/Engineering :: Physics
Requires-Python: >=3.9
Requires-Dist: numpy>=1.24.0
Requires-Dist: requests>=2.28.0
Requires-Dist: pydantic>=2.0.0
Provides-Extra: dev
Requires-Dist: pytest>=7.0.0; extra == "dev"
Requires-Dist: pytest-cov>=4.0.0; extra == "dev"
Requires-Dist: black>=23.0.0; extra == "dev"
Requires-Dist: ruff>=0.1.0; extra == "dev"
Requires-Dist: mypy>=1.0.0; extra == "dev"
Provides-Extra: mujoco
Requires-Dist: mujoco>=3.0.0; extra == "mujoco"
